fsapi/__init__.py
fsapi/__main__.py
fsapi/netconfig.py
fsapi/ecmascript/__init__.py
fsapi/ecmascript/__main__.py
fsapi/ecmascript/cli.py
fsapi/ecmascript/esbin.py
fsapi/ecmascript/opcode.py
fsapi/isu/__init__.py
fsapi/isu/__main__.py
fsapi/isu/cli.py
fsapi/isu/format.py
fsapi/isu/product.py
fsapi/isu/update.py
fsapi/isu/util.py
fsapi/net/__init__.py
fsapi/net/__main__.py
fsapi/net/_enum.py
fsapi/net/_nodes.py
fsapi/net/_wrap.py
fsapi/net/base.py
fsapi/net/cli.py
fsapi/net/device.py
fsapi_tools-2.0.4.dist-info/LICENSE
fsapi_tools-2.0.4.dist-info/METADATA
fsapi_tools-2.0.4.dist-info/WHEEL
fsapi_tools-2.0.4.dist-info/entry_points.txt
fsapi_tools-2.0.4.dist-info/top_level.txt
fsapi_tools-2.0.4.dist-info/RECORD
