Metadata-Version: 2.1
Name: fsapi-tools
Version: 2.0.4
Summary: Frontier Smart Firmware Tools and FSAPI Implementation.
Author-email: MatrixEditor <not@supported.com>
Project-URL: Homepage, https://github.com/MatrixEditor/frontier-smart-api
Project-URL: API-Docs, https://matrixeditor.github.io/frontier-smart-api/
Classifier: Development Status :: 5 - Production/Stable
Classifier: Intended Audience :: Science/Research
Classifier: License :: OSI Approved :: MIT License
Classifier: Programming Language :: Python :: 3.8
Classifier: Programming Language :: Python :: 3.9
Classifier: Programming Language :: Python :: 3.10
Classifier: Programming Language :: Python :: 3.11
License-File: LICENSE
